[
  {
    "id": "5318aec6-e474-4478-8882-0495657e4218",
    "nombre": "Finanzas",
    "jefeDepartamento": {
      "id": "53ece7ae-3ed0-49c0-b50d-0db04f50d367",
      "nombre": "Jefazo1",
      "fechaAlta": "abr 4, 2004",
      "contraseña": "esrthgs",
      "salario": 3500.0,
      "idDepartamento": "5318aec6-e474-4478-8882-0495657e4218"
    },
    "presupuesto": 250001.0,
    "proyectosTerminados": [
      {
        "idProyecto": "0e04d847-444d-4d39-9f0a-024a7191c193",
        "nombre": "Declaración de la renta",
        "idjefeProyecto": "7f784746-5819-gr43-ace7-978bcd3a9be1",
        "presupuesto": 29000.0,
        "fechaInicio": "oct 1, 2020",
        "fechaFin": "oct 1, 2020"
      },
      {
        "idProyecto": "1",
        "nombre": "PROYECTO_PRUEBA111",
        "idjefeProyecto": "7f784746-5819-gr43-ace7-978bcd3a9be1",
        "presupuesto": 5000.0,
        "fechaInicio": "nov 25, 3905",
        "fechaFin": "nov 25, 3906"
      },
      {
        "idProyecto": "3b923a39-9f94-4978-b415-17e3bbac617d",
        "nombre": "Estudio de mercado",
        "idjefeProyecto": "7f784746-5819-gr43-ace7-978bcd3a9be1",
        "presupuesto": 28000.0,
        "fechaInicio": "ago 1, 2021",
        "fechaFin": "nov 1, 2021"
      },
      {
        "idProyecto": "2ce6a8fb-d9cc-4c5e-94a7-f5739edaf1e6",
        "nombre": "Presupuestos 2022",
        "idjefeProyecto": "7f784746-5819-gr43-ace7-978bcd3a9be1",
        "presupuesto": 31000.0,
        "fechaInicio": "nov 1, 2021"
      },
      {
        "idProyecto": "45d64a82-7ebf-40ab-8278-fa3c3813c5ed",
        "nombre": "Balance económico",
        "idjefeProyecto": "7f784746-5819-gr43-ace7-978bcd3a9be1",
        "presupuesto": 30000.0,
        "fechaInicio": "oct 1, 2019",
        "fechaFin": "nov 1, 2021"
      },
      {
        "idProyecto": "6374ad58-ac34-4331-8ff1-a33f2f047107",
        "nombre": "Oportunidades nicho",
        "idjefeProyecto": "7f784746-5819-gr43-ace7-978bcd3a9be1",
        "presupuesto": 27000.0,
        "fechaInicio": "sept 2, 2021"
      }
    ],
    "proyectosDesarrollo": [
      {
        "idProyecto": "0e04d847-444d-4d39-9f0a-024a7191c193",
        "nombre": "Declaración de la renta",
        "idjefeProyecto": "7f784746-5819-gr43-ace7-978bcd3a9be1",
        "presupuesto": 29000.0,
        "fechaInicio": "oct 1, 2020",
        "fechaFin": "oct 1, 2020"
      },
      {
        "idProyecto": "1",
        "nombre": "PROYECTO_PRUEBA111",
        "idjefeProyecto": "7f784746-5819-gr43-ace7-978bcd3a9be1",
        "presupuesto": 5000.0,
        "fechaInicio": "nov 25, 3905",
        "fechaFin": "nov 25, 3906"
      },
      {
        "idProyecto": "3b923a39-9f94-4978-b415-17e3bbac617d",
        "nombre": "Estudio de mercado",
        "idjefeProyecto": "7f784746-5819-gr43-ace7-978bcd3a9be1",
        "presupuesto": 28000.0,
        "fechaInicio": "ago 1, 2021",
        "fechaFin": "nov 1, 2021"
      },
      {
        "idProyecto": "2ce6a8fb-d9cc-4c5e-94a7-f5739edaf1e6",
        "nombre": "Presupuestos 2022",
        "idjefeProyecto": "7f784746-5819-gr43-ace7-978bcd3a9be1",
        "presupuesto": 31000.0,
        "fechaInicio": "nov 1, 2021"
      },
      {
        "idProyecto": "45d64a82-7ebf-40ab-8278-fa3c3813c5ed",
        "nombre": "Balance económico",
        "idjefeProyecto": "7f784746-5819-gr43-ace7-978bcd3a9be1",
        "presupuesto": 30000.0,
        "fechaInicio": "oct 1, 2019",
        "fechaFin": "nov 1, 2021"
      },
      {
        "idProyecto": "6374ad58-ac34-4331-8ff1-a33f2f047107",
        "nombre": "Oportunidades nicho",
        "idjefeProyecto": "7f784746-5819-gr43-ace7-978bcd3a9be1",
        "presupuesto": 27000.0,
        "fechaInicio": "sept 2, 2021"
      }
    ],
    "presupuestoAnual": 145000.0,
    "historicoJefes": [
      {
        "id": "53ece7ae-3ed0-49c0-b50d-0db04f50d367",
        "nombre": "Jefazo1",
        "fechaAlta": "abr 4, 2004",
        "contraseña": "esrthgs",
        "salario": 3500.0,
        "idDepartamento": "5318aec6-e474-4478-8882-0495657e4218"
      }
    ]
  },
  {
    "id": "77e07771-35dc-4052-8d15-6f4622a7251f",
    "nombre": "Aplicaciones Moviles",
    "jefeDepartamento": {
      "id": "db53e2ff-6ab3-4830-ba3e-5ccd09d5650e",
      "nombre": "Jefazo4",
      "fechaAlta": "abr 4, 2004",
      "contraseña": "4asebhst",
      "salario": 3500.0,
      "idDepartamento": "77e07771-35dc-4052-8d15-6f4622a7251f"
    },
    "presupuesto": 500500.0,
    "proyectosTerminados": [
      {
        "idProyecto": "dbd80140-0035-4e1e-9e79-05dab9186dce",
        "nombre": "Transportes Ministerio",
        "idjefeProyecto": "af5ee0c4-eff0-40f0-9eff-e588a51504d7",
        "presupuesto": 80000.0,
        "fechaInicio": "oct 2, 2021",
        "fechaFin": "oct 1, 2020"
      },
      {
        "idProyecto": "50f4f6e5-f543-4d8d-a6bb-f7d1320f79a8",
        "nombre": "App EMT",
        "idjefeProyecto": "af5ee0c4-eff0-40f0-9eff-e588a51504d7",
        "presupuesto": 84000.0,
        "fechaInicio": "oct 2, 2021"
      },
      {
        "idProyecto": "e5a62f7a-5fe1-45a8-a389-d07411ae76b8",
        "nombre": "Organización datos DB",
        "idjefeProyecto": "af5ee0c4-eff0-40f0-9eff-e588a51504d7",
        "presupuesto": 86000.0,
        "fechaInicio": "oct 2, 2021"
      },
      {
        "idProyecto": "c17a5b25-ea70-4c8a-9b84-2d5d78e1cb37",
        "nombre": "Servicio NH",
        "idjefeProyecto": "af5ee0c4-eff0-40f0-9eff-e588a51504d7",
        "presupuesto": 90000.0,
        "fechaInicio": "oct 2, 2021",
        "fechaFin": "oct 1, 2020"
      }
    ],
    "proyectosDesarrollo": [
      {
        "idProyecto": "dbd80140-0035-4e1e-9e79-05dab9186dce",
        "nombre": "Transportes Ministerio",
        "idjefeProyecto": "af5ee0c4-eff0-40f0-9eff-e588a51504d7",
        "presupuesto": 80000.0,
        "fechaInicio": "oct 2, 2021",
        "fechaFin": "oct 1, 2020"
      },
      {
        "idProyecto": "50f4f6e5-f543-4d8d-a6bb-f7d1320f79a8",
        "nombre": "App EMT",
        "idjefeProyecto": "af5ee0c4-eff0-40f0-9eff-e588a51504d7",
        "presupuesto": 84000.0,
        "fechaInicio": "oct 2, 2021"
      },
      {
        "idProyecto": "e5a62f7a-5fe1-45a8-a389-d07411ae76b8",
        "nombre": "Organización datos DB",
        "idjefeProyecto": "af5ee0c4-eff0-40f0-9eff-e588a51504d7",
        "presupuesto": 86000.0,
        "fechaInicio": "oct 2, 2021"
      },
      {
        "idProyecto": "c17a5b25-ea70-4c8a-9b84-2d5d78e1cb37",
        "nombre": "Servicio NH",
        "idjefeProyecto": "af5ee0c4-eff0-40f0-9eff-e588a51504d7",
        "presupuesto": 90000.0,
        "fechaInicio": "oct 2, 2021",
        "fechaFin": "oct 1, 2020"
      }
    ],
    "presupuestoAnual": 425000.0,
    "historicoJefes": [
      {
        "id": "db53e2ff-6ab3-4830-ba3e-5ccd09d5650e",
        "nombre": "Jefazo4",
        "fechaAlta": "abr 4, 2004",
        "contraseña": "4asebhst",
        "salario": 3500.0,
        "idDepartamento": "77e07771-35dc-4052-8d15-6f4622a7251f"
      }
    ]
  },
  {
    "id": "7c0ea8ff-5da2-4991-8495-74814fad9634",
    "nombre": "Recursos humanos",
    "jefeDepartamento": {
      "id": "be30c85d-324c-4c79-bad8-96f220fd1355",
      "nombre": "Jefazo3",
      "fechaAlta": "abr 4, 2004",
      "contraseña": "daf876bt45a",
      "salario": 3500.0,
      "idDepartamento": "7c0ea8ff-5da2-4991-8495-74814fad9634"
    },
    "presupuesto": 125000.0,
    "proyectosTerminados": [
      {
        "idProyecto": "794b8cb2-3093-416d-87db-4d09ca5e5a68",
        "nombre": "Jornadas de acogida de nuevos trabajadores",
        "idjefeProyecto": "638ab226-b150-4e48-90fa-7190b9f47da1",
        "presupuesto": 38000.0,
        "fechaInicio": "oct 2, 2021",
        "fechaFin": "oct 1, 2020"
      },
      {
        "idProyecto": "80121180-9b3f-46b9-9e78-012dfe455a78",
        "nombre": "Reestructuración de personal",
        "idjefeProyecto": "638ab226-b150-4e48-90fa-7190b9f47da1",
        "presupuesto": 37000.0,
        "fechaInicio": "oct 2, 2021",
        "fechaFin": "oct 1, 2020"
      }
    ],
    "proyectosDesarrollo": [
      {
        "idProyecto": "794b8cb2-3093-416d-87db-4d09ca5e5a68",
        "nombre": "Jornadas de acogida de nuevos trabajadores",
        "idjefeProyecto": "638ab226-b150-4e48-90fa-7190b9f47da1",
        "presupuesto": 38000.0,
        "fechaInicio": "oct 2, 2021",
        "fechaFin": "oct 1, 2020"
      },
      {
        "idProyecto": "80121180-9b3f-46b9-9e78-012dfe455a78",
        "nombre": "Reestructuración de personal",
        "idjefeProyecto": "638ab226-b150-4e48-90fa-7190b9f47da1",
        "presupuesto": 37000.0,
        "fechaInicio": "oct 2, 2021",
        "fechaFin": "oct 1, 2020"
      }
    ],
    "presupuestoAnual": 75000.0,
    "historicoJefes": [
      {
        "id": "be30c85d-324c-4c79-bad8-96f220fd1355",
        "nombre": "Jefazo3",
        "fechaAlta": "abr 4, 2004",
        "contraseña": "daf876bt45a",
        "salario": 3500.0,
        "idDepartamento": "7c0ea8ff-5da2-4991-8495-74814fad9634"
      }
    ]
  },
  {
    "id": "e167f3d0-d333-4276-801d-50cfd29179e4",
    "nombre": "Desarrollo Web",
    "jefeDepartamento": {
      "id": "070f4608-0af7-4920-8e22-4ee3759517b9",
      "nombre": "Jefazo2",
      "fechaAlta": "abr 4, 2004",
      "contraseña": "65wsts",
      "salario": 3500.0,
      "idDepartamento": "e167f3d0-d333-4276-801d-50cfd29179e4"
    },
    "presupuesto": 450001.0,
    "proyectosTerminados": [
      {
        "idProyecto": "327f9d8b-e42b-4998-8522-b77282c39ddd",
        "nombre": "Web Santander",
        "idjefeProyecto": "503e1433-1f98-449c-b602-72ffde821e62",
        "presupuesto": 125000.0,
        "fechaInicio": "oct 2, 2021",
        "fechaFin": "nov 1, 2021"
      },
      {
        "idProyecto": "e85905a3-d518-4f4d-8af7-b8392427e304",
        "nombre": "Wordpress Prisa",
        "idjefeProyecto": "503e1433-1f98-449c-b602-72ffde821e62",
        "presupuesto": 130000.0,
        "fechaInicio": "oct 2, 2021"
      },
      {
        "idProyecto": "98452ba4-3442-49a1-b204-d09b97972706",
        "nombre": "Reestructuracion Google",
        "idjefeProyecto": "503e1433-1f98-449c-b602-72ffde821e62",
        "presupuesto": 120000.0,
        "fechaInicio": "oct 2, 2021"
      },
      {
        "idProyecto": "65521399-1fc0-4085-bc18-f0f43e211508",
        "nombre": "CAMBIO NOMBRE AL RESTAURANT",
        "idjefeProyecto": "503e1433-1f98-449c-b602-72ffde821e62",
        "presupuesto": 5000.0,
        "fechaInicio": "nov 25, 3905",
        "fechaFin": "nov 25, 3906"
      }
    ],
    "proyectosDesarrollo": [
      {
        "idProyecto": "327f9d8b-e42b-4998-8522-b77282c39ddd",
        "nombre": "Web Santander",
        "idjefeProyecto": "503e1433-1f98-449c-b602-72ffde821e62",
        "presupuesto": 125000.0,
        "fechaInicio": "oct 2, 2021",
        "fechaFin": "nov 1, 2021"
      },
      {
        "idProyecto": "e85905a3-d518-4f4d-8af7-b8392427e304",
        "nombre": "Wordpress Prisa",
        "idjefeProyecto": "503e1433-1f98-449c-b602-72ffde821e62",
        "presupuesto": 130000.0,
        "fechaInicio": "oct 2, 2021"
      },
      {
        "idProyecto": "98452ba4-3442-49a1-b204-d09b97972706",
        "nombre": "Reestructuracion Google",
        "idjefeProyecto": "503e1433-1f98-449c-b602-72ffde821e62",
        "presupuesto": 120000.0,
        "fechaInicio": "oct 2, 2021"
      },
      {
        "idProyecto": "65521399-1fc0-4085-bc18-f0f43e211508",
        "nombre": "CAMBIO NOMBRE AL RESTAURANT",
        "idjefeProyecto": "503e1433-1f98-449c-b602-72ffde821e62",
        "presupuesto": 5000.0,
        "fechaInicio": "nov 25, 3905",
        "fechaFin": "nov 25, 3906"
      }
    ],
    "presupuestoAnual": 375000.0,
    "historicoJefes": [
      {
        "id": "070f4608-0af7-4920-8e22-4ee3759517b9",
        "nombre": "Jefazo2",
        "fechaAlta": "abr 4, 2004",
        "contraseña": "65wsts",
        "salario": 3500.0,
        "idDepartamento": "e167f3d0-d333-4276-801d-50cfd29179e4"
      }
    ]
  }
]